exact.cpython-312-x86_64-linux-gnu.so
constraints/Constr.cpp
constraints/Constr.hpp
constraints/ConstrExp.cpp
constraints/ConstrExp.hpp
constraints/ConstrExpPools.cpp
constraints/ConstrExpPools.hpp
constraints/ConstrSimple.cpp
constraints/ConstrSimple.hpp
datastructures/Heuristic.cpp
datastructures/Heuristic.hpp
datastructures/IntMap.hpp
datastructures/IntSet.cpp
datastructures/IntSet.hpp
datastructures/SolverStructs.cpp
datastructures/SolverStructs.hpp
external/ankerl/LICENSE
external/ankerl/unordered_dense.h
external/doctest/LICENSE.txt
external/doctest/doctest.h
external/doctest/main.cpp
external/gzstream/COPYING.LIB
external/gzstream/gzstream.h
external/plf/plf_reorderase.h
interface/Exact.cpp
interface/Exact.hpp
interface/IntConstraint.cpp
interface/IntConstraint.hpp
interface/IntProg.cpp
interface/IntProg.hpp
propagation/Equalities.cpp
propagation/Equalities.hpp
propagation/Implications.cpp
propagation/Implications.hpp
propagation/LpSolver.cpp
propagation/LpSolver.hpp
propagation/Propagator.cpp
propagation/Propagator.hpp
tests/algorithms.cpp
tests/inferences.cpp
tests/input.cpp
tests/memory.cpp
tests/optimization.cpp
used_licenses/COPYING
used_licenses/COPYING.cpp
used_licenses/COPYING.hpp
used_licenses/EPL.cpp
used_licenses/EPL.hpp
used_licenses/EPL.txt
used_licenses/MIT.cpp
used_licenses/MIT.hpp
used_licenses/MIT.txt
used_licenses/boost.cpp
used_licenses/boost.hpp
used_licenses/boost.txt
used_licenses/licenses.cpp
used_licenses/licenses.hpp
used_licenses/roundingsat.cpp
used_licenses/roundingsat.hpp
used_licenses/roundingsat.txt
used_licenses/zib_apache.cpp
used_licenses/zib_apache.hpp
used_licenses/zib_apache.txt
exact-2.2.1.dist-info/METADATA
exact-2.2.1.dist-info/WHEEL
exact-2.2.1.dist-info/top_level.txt
exact-2.2.1.dist-info/RECORD
exact-2.2.1.dist-info/licenses/LICENSE
