Metadata-Version: 2.4
Name: Exact
Version: 2.2.1
Summary: Python bindings for Exact
Author-email: Jo Devriendt <jo.devriendt@nonfictionsoftware.com>
License: AGPL-3.0-only
Project-URL: Homepage, https://gitlab.com/nonfiction-software/exact
Project-URL: Issues, https://gitlab.com/nonfiction-software/exact/-/issues
Classifier: Programming Language :: Python :: 3
Requires-Python: >=3.10
License-File: LICENSE
Dynamic: license-file
